<?xml version="1.0" encoding="UTF-8"?><record_update table="sp_instance">
    <sp_instance action="INSERT_OR_UPDATE">
        <active>true</active>
        <class_name/>
        <color>default</color>
        <css/>
        <glyph/>
        <id/>
        <order>1</order>
        <roles/>
        <short_description/>
        <size>md</size>
        <sp_column display_value="1">0b7ad5a52fc14110ee00d5f62799b659</sp_column>
        <sp_widget display_value="GLA Homepage">4b7a08992fc10110ee00d5f62799b626</sp_widget>
        <sys_class_name>sp_instance</sys_class_name>
        <sys_created_by>admin</sys_created_by>
        <sys_created_on>2022-01-19 08:57:56</sys_created_on>
        <sys_id>f6bba68b2f810110ee00d5f62799b6bd</sys_id>
        <sys_mod_count>0</sys_mod_count>
        <sys_name/>
        <sys_package display_value="German Learning" source="x_723119_germanlrn">612b9ab72f100110ee00d5f62799b622</sys_package>
        <sys_policy/>
        <sys_scope display_value="German Learning">612b9ab72f100110ee00d5f62799b622</sys_scope>
        <sys_update_name>sp_instance_f6bba68b2f810110ee00d5f62799b6bd</sys_update_name>
        <sys_updated_by>admin</sys_updated_by>
        <sys_updated_on>2022-01-19 08:57:56</sys_updated_on>
        <title/>
        <url/>
        <widget_parameters/>
    </sp_instance>
    <sys_translated_text action="delete_multiple" query="documentkey=f6bba68b2f810110ee00d5f62799b6bd"/>
</record_update>
