<?xml version="1.0" encoding="UTF-8"?><record_update table="sp_container">
    <sp_container action="DELETE">
        <background_color/>
        <background_image/>
        <background_style>default</background_style>
        <bootstrap_alt>false</bootstrap_alt>
        <class_name/>
        <container_class_name>homework</container_class_name>
        <name>Copy of Welcome (1) - Container 1</name>
        <order>1</order>
        <sp_page display_value="copy_of_gla_homepage_1">fd8f12fa2f450110ee00d5f62799b6a9</sp_page>
        <subheader>false</subheader>
        <sys_class_name>sp_container</sys_class_name>
        <sys_created_by>mdaniel</sys_created_by>
        <sys_created_on>2022-01-18 13:52:14</sys_created_on>
        <sys_id>d4856efe2f450110ee00d5f62799b6a6</sys_id>
        <sys_mod_count>3</sys_mod_count>
        <sys_name>Copy of Welcome (1) - Container 1</sys_name>
        <sys_package display_value="German Learning" source="x_723119_germanlrn">612b9ab72f100110ee00d5f62799b622</sys_package>
        <sys_policy/>
        <sys_scope display_value="German Learning">612b9ab72f100110ee00d5f62799b622</sys_scope>
        <sys_update_name>sp_container_d4856efe2f450110ee00d5f62799b6a6</sys_update_name>
        <sys_updated_by>mdaniel</sys_updated_by>
        <sys_updated_on>2022-01-19 08:28:33</sys_updated_on>
        <title/>
        <width>container</width>
    </sp_container>
    <sys_update_version action="INSERT_OR_UPDATE">
        <action>DELETE</action>
        <application display_value="German Learning">612b9ab72f100110ee00d5f62799b622</application>
        <file_path/>
        <instance_id>7549a605db5f049442b321c4059619e1</instance_id>
        <instance_name>dev101723</instance_name>
        <name>sp_container_d4856efe2f450110ee00d5f62799b6a6</name>
        <payload><![CDATA[<?xml version="1.0" encoding="UTF-8"?><record_update table="sp_container"><sp_container action="INSERT_OR_UPDATE"><background_color/><background_image/><background_style>default</background_style><bootstrap_alt>false</bootstrap_alt><class_name/><container_class_name>homework</container_class_name><name>Copy of Welcome (1) - Container 1</name><order>1</order><sp_page display_value="copy_of_gla_homepage_1">fd8f12fa2f450110ee00d5f62799b6a9</sp_page><subheader>false</subheader><sys_class_name>sp_container</sys_class_name><sys_created_by>mdaniel</sys_created_by><sys_created_on>2022-01-18 13:52:14</sys_created_on><sys_id>d4856efe2f450110ee00d5f62799b6a6</sys_id><sys_mod_count>3</sys_mod_count><sys_name>Copy of Welcome (1) - Container 1</sys_name><sys_package display_value="German Learning" source="x_723119_germanlrn">612b9ab72f100110ee00d5f62799b622</sys_package><sys_policy/><sys_scope display_value="German Learning">612b9ab72f100110ee00d5f62799b622</sys_scope><sys_update_name>sp_container_d4856efe2f450110ee00d5f62799b6a6</sys_update_name><sys_updated_by>mdaniel</sys_updated_by><sys_updated_on>2022-01-19 08:28:33</sys_updated_on><title/><width>container</width></sp_container></record_update>]]></payload>
        <payload_hash>1401735508</payload_hash>
        <record_name>Copy of Welcome (1) - Container 1</record_name>
        <reverted_from/>
        <source>a52b9ab72f100110ee00d5f62799b624</source>
        <source_table>sys_update_set</source_table>
        <state>previous</state>
        <sys_created_by>mdaniel</sys_created_by>
        <sys_created_on>2022-01-19 08:28:33</sys_created_on>
        <sys_id>140562472f810110ee00d5f62799b6de</sys_id>
        <sys_mod_count>0</sys_mod_count>
        <sys_recorded_at>17e7173aca20000001</sys_recorded_at>
        <sys_updated_by>mdaniel</sys_updated_by>
        <sys_updated_on>2022-01-19 08:28:33</sys_updated_on>
        <type>Container</type>
        <update_guid>5c05624798810110f2bcb4ab8fb7fddd</update_guid>
        <update_guid_history>5c05624798810110f2bcb4ab8fb7fddd:1401735508,fb666e323f850110a60b199e44a2908c:764923253,d9666a32e48501103f0bc6f8cdda4ed7:911705531,5c85623290850110a93d70bdafcceb1a:-755525609</update_guid_history>
    </sys_update_version>
    <sys_metadata_delete action="INSERT_OR_UPDATE">
        <sys_audit_delete display_value="Copy of Welcome (1) - Container 1">390522472f810110ee00d5f62799b6b7</sys_audit_delete>
        <sys_class_name>sys_metadata_delete</sys_class_name>
        <sys_created_by>mdaniel</sys_created_by>
        <sys_created_on>2022-01-19 08:28:39</sys_created_on>
        <sys_db_object display_value="" name="sp_container">sp_container</sys_db_object>
        <sys_id>342641857661407a80351ccc9a744b29</sys_id>
        <sys_metadata>d4856efe2f450110ee00d5f62799b6a6</sys_metadata>
        <sys_mod_count>0</sys_mod_count>
        <sys_name>Copy of Welcome (1) - Container 1</sys_name>
        <sys_package display_value="German Learning" source="x_723119_germanlrn">612b9ab72f100110ee00d5f62799b622</sys_package>
        <sys_parent/>
        <sys_policy/>
        <sys_scope display_value="German Learning">612b9ab72f100110ee00d5f62799b622</sys_scope>
        <sys_scope_delete display_value="">0512347fbadb48889a058a15e6fdcaa4</sys_scope_delete>
        <sys_update_name>sp_container_d4856efe2f450110ee00d5f62799b6a6</sys_update_name>
        <sys_update_version display_value="sp_container_d4856efe2f450110ee00d5f62799b6a6">140562472f810110ee00d5f62799b6de</sys_update_version>
        <sys_updated_by>mdaniel</sys_updated_by>
        <sys_updated_on>2022-01-19 08:28:39</sys_updated_on>
    </sys_metadata_delete>
</record_update>
